plums/__init__.py
plums/commons/__init__.py
plums/commons/path.py
plums/commons/data/__init__.py
plums/commons/data/base.py
plums/commons/data/data.py
plums/commons/data/mask.py
plums/commons/data/mixin.py
plums/commons/data/record.py
plums/commons/data/tile.py
plums/commons/data/taxonomy/__init__.py
plums/commons/data/taxonomy/accessor.py
plums/commons/data/taxonomy/iterator.py
plums/commons/data/taxonomy/label.py
plums/commons/data/taxonomy/tree.py
plums/dataflow/__init__.py
plums/dataflow/dataset/__init__.py
plums/dataflow/dataset/base.py
plums/dataflow/dataset/pattern.py
plums/dataflow/dataset/playground.py
plums/dataflow/io/__init__.py
plums/dataflow/io/json.py
plums/dataflow/io/tile/__init__.py
plums/dataflow/io/tile/_backend.py
plums/dataflow/io/tile/tile.py
plums/dataflow/io/tile/_format/__init__.py
plums/dataflow/io/tile/_format/channels.py
plums/dataflow/io/tile/_format/ptype.py
plums/dataflow/io/tile/_format/utils.py
plums/dataflow/io/tile/_vendor/__init__.py
plums/dataflow/io/tile/_vendor/turbojpeg.py
plums/dataflow/utils/__init__.py
plums/dataflow/utils/cache.py
plums/dataflow/utils/path.py
plums/dataflow/utils/parser/__init__.py
plums/dataflow/utils/parser/exceptions.py
plums/dataflow/utils/parser/grammar.lark
plums/dataflow/utils/parser/parser.py
plums/dataflow/utils/parser/resolver.py
plums/dataflow/utils/parser/validator.py
plums/model/__init__.py
plums/model/exception.py
plums/model/model.py
plums/model/components/__init__.py
plums/model/components/components.py
plums/model/components/utils.py
plums/model/components/version.py
plums/model/validation/__init__.py
plums/model/validation/metadata.py
plums/model/validation/schema_core.py
plums/model/validation/structure.py
plums/model/validation/utils/__init__.py
plums/model/validation/utils/checksum.py
plums/model/validation/utils/dict_from_tree.py
plums/model/validation/utils/validate_path.py
plums/plot/__init__.py
plums/plot/plot.py
plums/plot/engine/__init__.py
plums/plot/engine/color_engine.py
plums-0.5.2.dist-info/LICENSE
plums-0.5.2.dist-info/METADATA
plums-0.5.2.dist-info/WHEEL
plums-0.5.2.dist-info/top_level.txt
plums-0.5.2.dist-info/RECORD
